bsn_sdk_py/__init__.py
bsn_sdk_py/client/__init__.py
bsn_sdk_py/client/base_client.py
bsn_sdk_py/client/bsn_enum.py
bsn_sdk_py/client/config.py
bsn_sdk_py/client/exceptions.py
bsn_sdk_py/client/chainmaker/__init__.py
bsn_sdk_py/client/chainmaker/chainmaker_client.py
bsn_sdk_py/client/chainmaker/entity/__init__.py
bsn_sdk_py/client/chainmaker/entity/bsn_base.py
bsn_sdk_py/client/chainmaker/entity/event_query.py
bsn_sdk_py/client/chainmaker/entity/event_register.py
bsn_sdk_py/client/chainmaker/entity/event_remove.py
bsn_sdk_py/client/chainmaker/entity/get_block_height.py
bsn_sdk_py/client/chainmaker/entity/get_block_info.py
bsn_sdk_py/client/chainmaker/entity/get_tx_info.py
bsn_sdk_py/client/chainmaker/entity/req_chain_code.py
bsn_sdk_py/client/chainmaker/entity/sdk_trans.py
bsn_sdk_py/client/chainmaker/entity/user_enroll.py
bsn_sdk_py/client/chainmaker/entity/user_register.py
bsn_sdk_py/common/__init__.py
bsn_sdk_py/common/aes.py
bsn_sdk_py/common/api_requestor.py
bsn_sdk_py/common/bsn_encrypt.py
bsn_sdk_py/common/myecdsa256.py
bsn_sdk_py/common/sm.py
bsn_sdk_py/test/__init__.py
bsn_sdk_py/test/chainmaker_simple_test.py
bsn_sdk_py/test/chainmaker_test.py
bsn_sdk_py/test/hll.py
bsn_sdk_py/test/test_keypair_quick.py
bsn_sdk_py/trans/__init__.py
bsn_sdk_py/trans/chainmaker/__init__.py
bsn_sdk_py/trans/chainmaker/chainmaker_not_trust_trans_request.py
bsn_sdk_py/trans/chainmaker/chainmaker_transaction_header.py
bsn_sdk_py/until/__init__.py
bsn_sdk_py/until/bsn_logger.py
bsn_sdk_py/until/crypto_utils.py
bsn_sdk_py/until/file_utils.py
bsn_sdk_py/until/logger_test.py
bsn_sdk_py/until/tools.py
bsn_sdk_py/until/gm/__init__.py
bsn_sdk_py/until/gm/ec.py
bsn_sdk_py/until/gm/func.py
bsn_sdk_py/until/gm/sm2.py
bsn_sdk_py/until/gm/sm3.py
bsn_sdk_py/until/gm/sm4.py
bsn_chainmaker_sdk_py-1.0.0.dist-info/LICENSE
bsn_chainmaker_sdk_py-1.0.0.dist-info/METADATA
bsn_chainmaker_sdk_py-1.0.0.dist-info/WHEEL
bsn_chainmaker_sdk_py-1.0.0.dist-info/top_level.txt
bsn_chainmaker_sdk_py-1.0.0.dist-info/RECORD
