Metadata-Version: 2.1
Name: bsn_chainmaker_sdk_py
Version: 1.0.0
Summary: BSN PCN Gateway SDK for Python - Chainmaker blockchain framework support
Author-email: helailiang <helailiang@reddatetech.com>
License: MIT
Project-URL: Homepage, http://gitlab.bsnbase.com:8088/sbp-di/oc/sbp-pcng-chainmaker-py-sdk
Project-URL: Repository, http://gitlab.bsnbase.com:8088/sbp-di/oc/sbp-pcng-chainmaker-py-sdk
Keywords: bsn,chainmaker,bsnbase,bsn_sdk_py,bsn_sdk_python,blockchain,pcn,gateway
Classifier: Programming Language :: Python :: 3.8
Classifier: License :: OSI Approved :: MIT License
Classifier: Operating System :: OS Independent
Classifier: Topic :: Software Development :: Libraries :: Python Modules
Classifier: Topic :: Internet
Classifier: Intended Audience :: Developers
Requires-Python: >=3.8
License-File: LICENSE
Requires-Dist: hkdf==0.0.3
Requires-Dist: cryptography==41.0.2
Requires-Dist: fabric-sdk-py==0.8.1
Requires-Dist: pyOpenSSL==23.2.0
Requires-Dist: grpcio>=1.56.2
Requires-Dist: protobuf>=3.19.0
Requires-Dist: requests>=2.20.0
